aprint/__init__.py
aprint/aprint.py
aprint/iterators/__init__.py
aprint/iterators/dispatch.py
aprint/iterators/python.py
aprint/objects/__init__.py
aprint/objects/dispatch.py
aprint/objects/numpy.py
aprint/objects/torch.py
aprint-0.0.2.dist-info/LICENSE
aprint-0.0.2.dist-info/METADATA
aprint-0.0.2.dist-info/WHEEL
aprint-0.0.2.dist-info/top_level.txt
aprint-0.0.2.dist-info/RECORD
