Metadata-Version: 2.1
Name: aprint
Version: 0.0.2
Summary: A function to print arrays in a concise way
Home-page: https://github.com/huangyxi/aprint
Author: HUANG Yuxi
Author-email: aprint@hyxi.dev
License: MIT License
Keywords: aprint,print
Platform: any
License-File: LICENSE
